apipt/__init__.py
apipt/app.py
apipt/command.py
apipt/common.py
apipt-0.1.1.dist-info/LICENSE
apipt-0.1.1.dist-info/METADATA
apipt-0.1.1.dist-info/WHEEL
apipt-0.1.1.dist-info/entry_points.txt
apipt-0.1.1.dist-info/top_level.txt
apipt-0.1.1.dist-info/RECORD
