Metadata-Version: 2.1
Name: apipt
Version: 0.1.1
Summary: Install Python packages by apt
Home-page: https://github.com/KumaTea/apipt
Author: KumaTea
Author-email: contact@maku.ml
License: MIT
Keywords: apipt
Platform: posix
Classifier: Programming Language :: Python :: 3
Classifier: Programming Language :: Python :: 3.6
Classifier: Programming Language :: Python :: 3.7
Classifier: Programming Language :: Python :: 3.8
Classifier: Programming Language :: Python :: 3.9
Classifier: Development Status :: 4 - Beta
Classifier: License :: OSI Approved :: MIT License
Classifier: Operating System :: POSIX :: Linux
Classifier: Topic :: Utilities
Requires-Python: >=3.6
Requires-Dist: lz4
